lseg_analytics/core/__init__.py
lseg_analytics/core/exceptions.py
lseg_analytics/core/py.typed
lseg_analytics/core/sdk_session.py
lseg_analytics/core/_credentials/__init__.py
lseg_analytics/core/_credentials/_logger.py
lseg_analytics/core/_credentials/config.py
lseg_analytics/core/_credentials/loopback_client.py
lseg_analytics/core/_credentials/machine_token_credential.py
lseg_analytics/core/_credentials/user_token_credential.py
lseg_analytics/core/common/__init__.py
lseg_analytics/core/common/_resource_base.py
lseg_analytics/core/common/_utils.py
lseg_analytics/core/config/__init__.py
lseg_analytics/core/config/_configuration.py
lseg_analytics/core/logging/__init__.py
lseg_analytics/core/logging/_config.py
lseg_analytics/core/logging/_logger.py
lseg_analytics/core/metadata/lookup_table.json
lseg_analytics/core/metadata/lseg_analytics.core.common.json
lseg_analytics/core/metadata/lseg_analytics.core.config.json
lseg_analytics/core/metadata/lseg_analytics.core.exceptions.json
lseg_analytics/core/metadata/lseg_analytics.core.logging.json
lseg_analytics/core/metadata/lseg_analytics.core.sdk_session.json
lseg_analytics_core-1.1.0.dist-info/licenses/LICENSE
lseg_analytics_core-1.1.0.dist-info/METADATA
lseg_analytics_core-1.1.0.dist-info/WHEEL
lseg_analytics_core-1.1.0.dist-info/top_level.txt
lseg_analytics_core-1.1.0.dist-info/RECORD
