Metadata-Version: 2.4
Name: lseg-analytics-core
Version: 1.1.0
Summary: LSEG Analytics SDK core for Python
Author-email: analyticssdk <analyticssdk@lseg.com>
Maintainer-email: analyticssdk <analyticssdk@lseg.com>
Requires-Python: >=3.8
License-File: LICENSE
Requires-Dist: corehttp==1.0.0b5
Requires-Dist: python-dotenv
Requires-Dist: requests
Requires-Dist: isodate<1.0.0,>=0.6.1
Requires-Dist: Flask[async]
Requires-Dist: pkce
Requires-Dist: requests_oauthlib
Requires-Dist: flask-wtf
Dynamic: license-file
